tmux_fork/__init__.py
tmux_fork/main.py
tmux_fork-1.0.0.dist-info/METADATA
tmux_fork-1.0.0.dist-info/WHEEL
tmux_fork-1.0.0.dist-info/entry_points.txt
tmux_fork-1.0.0.dist-info/top_level.txt
tmux_fork-1.0.0.dist-info/RECORD
