Metadata-Version: 2.4
Name: tmux-fork
Version: 1.0.0
Summary: Fork current tmux window to a new window in the same directory
Author: Your Name
License: MIT
Project-URL: Homepage, https://github.com/talwrii/tmux-fork
Classifier: Environment :: Console
Classifier: Intended Audience :: Developers
Classifier: License :: OSI Approved :: MIT License
Classifier: Operating System :: POSIX
Classifier: Programming Language :: Python :: 3
Classifier: Topic :: Utilities
Requires-Python: >=3.7
